gdiaz_my_calc_2025-1.2.dist-info/licenses/LICENSE
mi_calculadora/__init__.py
mi_calculadora/operaciones.py
gdiaz_my_calc_2025-1.2.dist-info/METADATA
gdiaz_my_calc_2025-1.2.dist-info/WHEEL
gdiaz_my_calc_2025-1.2.dist-info/top_level.txt
gdiaz_my_calc_2025-1.2.dist-info/RECORD
