Metadata-Version: 2.4
Name: gdiaz-my-calc-2025
Version: 1.2
Summary: Una librería simple de Python con operaciones matemáticas básicas.
Author-email: Godofredo Diaz <gdiaz@tecsup.edu.pe>
License: Apache-2.0
Project-URL: Homepage, https://github.com/gdiazesp/mi-calculadora-proyecto
Project-URL: Repository, https://github.com/gdiazesp/mi-calculadora-proyecto
Project-URL: Bug Tracker, https://github.com/gdiazesp/mi-calculadora-proyecto/issues
Keywords: calculadora,matemáticas,básico,operaciones
Classifier: Development Status :: 3 - Alpha
Classifier: Intended Audience :: Developers
Classifier: Intended Audience :: Education
Classifier: Topic :: Software Development :: Libraries :: Python Modules
Classifier: Topic :: Scientific/Engineering :: Mathematics
Classifier: License :: OSI Approved :: Apache Software License
Classifier: Programming Language :: Python :: 3
Classifier: Programming Language :: Python :: 3.7
Classifier: Programming Language :: Python :: 3.8
Classifier: Programming Language :: Python :: 3.9
Classifier: Programming Language :: Python :: 3.10
Classifier: Programming Language :: Python :: 3.11
Classifier: Programming Language :: Python :: 3.12
Classifier: Operating System :: OS Independent
Requires-Python: >=3.7
License-File: LICENSE
Dynamic: license-file
